{"is_source_file": true, "format": "JavaScript (React JSX)", "description": "This file is the main entry point for a React application. It imports necessary modules, styles, and the main App component, then renders the App into the DOM within React's StrictMode.", "external_files": ["react", "react-dom/client", "./index.css", "./App.jsx"], "external_methods": ["React.createRoot", "React.StrictMode.render"], "published": [], "classes": [], "methods": [{"name": "createRoot", "description": "Initializes the React application root targeting the DOM element with id 'root'."}], "calls": ["createRoot(document.getElementById('root')).render"], "search-terms": ["React", "Main entry point", "render", "DOM mounting", "jsx"], "state": 2, "file_id": 10, "knowledge_revision": 23, "git_revision": "fc31919341d7d2b4b5a4c5eaf123de3084e28f0b", "ctags": [], "hash": "e13723e2574429d9a6d849727e3ff695", "format-version": 4, "code-base-name": "mytv_frontend", "filename": "mytv_frontend/src/main.jsx", "revision_history": [{"23": "fc31919341d7d2b4b5a4c5eaf123de3084e28f0b"}]}